{
    "id": "7e6215340ace5fdd85cc5e1446cab2ec0a3810009e0290d797accc59a9b0cf9b",
    "title": "Waymo partners with Toyota to bring autonomous driving to personal vehicles",
    "link": "https://waymo.com/blog/2025/04/waymo-and-toyota-outline-strategic-partnership",
    "published_iso": "2025-04-29T23:06:02",
    "summary": "<a href=\"https://news.ycombinator.com/item?id=43839123\">Comments</a>",
    "source_feed": "https://news.ycombinator.com/rss",
    "scraped_at_iso": "2025-04-30T00:55:33.263582"
}