{
    "id": "d12c3417bb5a6dfeb5953bed99de0ff1232b8614a935fa4bc7cbf15f636acad1",
    "title": "Meta needs to win over AI developers at its first LlamaCon",
    "link": "https://techcrunch.com/2025/04/29/meta-needs-to-win-over-ai-developers-at-its-first-llamacon/",
    "published_iso": "2025-04-29T15:20:46",
    "summary": "On Tuesday, Meta is hosting its first-ever LlamaCon AI developer conference at its Menlo Park headquarters, where the company will try to pitch developers on building applications with its open Llama AI models. Just a year ago, that wasn&#8217;t a hard sell. However, in recent months, Meta has struggled to keep up with both &#8220;open&#8221; [&#8230;]",
    "source_feed": "https://techcrunch.com/feed/",
    "scraped_at_iso": "2025-04-30T01:25:51.679960"
}